iac_test/__init__.py
iac_test/__main__.py
iac_test/ansible_vault.py
iac_test/cli/__init__.py
iac_test/cli/main.py
iac_test/cli/options.py
iac_test/pabot.py
iac_test/robot_writer.py
iac_test/yaml.py
iac_test-0.2.6.dist-info/LICENSE
iac_test-0.2.6.dist-info/METADATA
iac_test-0.2.6.dist-info/WHEEL
iac_test-0.2.6.dist-info/entry_points.txt
iac_test-0.2.6.dist-info/RECORD
