Metadata-Version: 2.1
Name: iac-test
Version: 0.2.6
Summary: A CLI tool to render and execute Robot Framework tests using Jinja templating.
Home-page: https://github.com/netascode/iac-test
License: LICENSE
Author: Daniel Schmidt
Author-email: danischm@cisco.com
Maintainer: Daniel Schmidt
Maintainer-email: danischm@cisco.com
Requires-Python: >=3.8,<4.0
Classifier: License :: Other/Proprietary License
Classifier: Programming Language :: Python :: 3
Classifier: Programming Language :: Python :: 3.8
Classifier: Programming Language :: Python :: 3.9
Classifier: Programming Language :: Python :: 3.10
Classifier: Programming Language :: Python :: 3.11
Classifier: Programming Language :: Python :: 3.12
Requires-Dist: Jinja2 (>=3.0.3,<4.0.0)
Requires-Dist: RESTinstance (>=1.3.0,<2.0.0)
Requires-Dist: click (>=8.0.4,<9.0.0)
Requires-Dist: errorhandler (>=2.0.1,<3.0.0)
Requires-Dist: importlib-metadata (>=2.0.0,<3.0.0)
Requires-Dist: jmespath (>=1.0.1,<2.0.0)
Requires-Dist: robotframework (>=6.0.1,<7.0.0)
Requires-Dist: robotframework-jsonlibrary (>=0.5,<0.6)
Requires-Dist: robotframework-pabot (>=2.8.0,<3.0.0)
Requires-Dist: robotframework-requests (>=0.9.4,<0.10.0)
Requires-Dist: ruamel-yaml (>0.16.10)
Project-URL: Documentation, https://github.com/netascode/iac-test
Project-URL: Repository, https://github.com/netascode/iac-test
